video_to_audio_converter/__init__.py
video_to_audio_converter/converter.py
video_to_audio_converter-0.1.1.dist-info/METADATA
video_to_audio_converter-0.1.1.dist-info/WHEEL
video_to_audio_converter-0.1.1.dist-info/RECORD
