Metadata-Version: 2.3
Name: video-to-audio-converter
Version: 0.1.1
Summary: 
Author: Your Name
Author-email: you@example.com
Requires-Python: >=3.9
Classifier: Programming Language :: Python :: 3
Classifier: Programming Language :: Python :: 3.9
Classifier: Programming Language :: Python :: 3.10
Classifier: Programming Language :: Python :: 3.11
Classifier: Programming Language :: Python :: 3.12
Classifier: Programming Language :: Python :: 3.13
Requires-Dist: decorator (>=4.4.2,<5.0.0)
Requires-Dist: imageio-ffmpeg (>=0.6.0,<0.7.0)
Requires-Dist: moviepy (==1.0.3)
Requires-Dist: numpy (>=1.24.0,<2.0.0)
